octo/__init__.py
octo/base.py
octo/commands/__init__.py
octo/commands/manager.py
octo/commands/startapp.py
octo/commands/startproject.py
octo/commands/generate/__init__.py
octo/commands/generate/utils.py
octo/commands/generate/repositories/__init__.py
octo/commands/generate/repositories/octo_launch.py
octo/conf/__init__.py
octo/conf/app_template/__init__.py-tpl
octo/conf/app_template/admin.py-tpl
octo/conf/app_template/apps.py-tpl
octo/conf/app_template/models.py-tpl
octo/conf/app_template/urls.py-tpl
octo/conf/app_template/migrations/__init__.py-tpl
octo/conf/app_template/serializers/__init__.py-tpl
octo/conf/app_template/tests/__init__.py-tpl
octo/conf/app_template/views/__init__.py-tpl
octo/handler/__init__.py
octo/handler/cache.py
octo/handler/clean.py
octo/handler/command.py
octo/handler/github.py
octo/handler/manager.py
octo/handler/oauth.py
octo/handler/social/__init__.py
octo/handler/social/google.py
octo/logging/__init__.py
octo/logging/config.py
octo/logging/general.py
octo/utils/__init__.py
octo/utils/generate.py
octo/utils/image.py
octo_framework-1.0.2.dist-info/licenses/LICENSE
octo_framework-1.0.2.dist-info/METADATA
octo_framework-1.0.2.dist-info/WHEEL
octo_framework-1.0.2.dist-info/entry_points.txt
octo_framework-1.0.2.dist-info/top_level.txt
octo_framework-1.0.2.dist-info/RECORD
