Metadata-Version: 2.4
Name: octo-framework
Version: 1.0.2
Summary: Octo-Framework is a framework designed to simplify the setup and development process for Django projects. It is based on the Octo-Lunch template and provides a set of tools and features that help developers build robust and flexible web applications faster and more efficiently.
Author-email: Octo Software <octo.team.dev@gmail.com>
License: MIT License
Project-URL: Homepage, https://github.com/oc-to/octo-framework
Project-URL: Bug Tracker, https://github.com/oc-to/octo-framework/issues
Classifier: Development Status :: 5 - Production/Stable
Classifier: Intended Audience :: Developers
Classifier: Intended Audience :: Information Technology
Classifier: Intended Audience :: System Administrators
Classifier: Framework :: Django
Classifier: Framework :: Django :: 4.0
Classifier: Framework :: Django :: 5.0
Classifier: License :: OSI Approved :: MIT License
Classifier: Programming Language :: Python
Classifier: Programming Language :: Python :: 3.11
Classifier: Programming Language :: Python :: 3.12
Classifier: Operating System :: OS Independent
Classifier: Operating System :: Microsoft :: Windows
Classifier: Operating System :: MacOS :: MacOS X
Classifier: Operating System :: POSIX :: Linux
Requires-Python: >=3.11
License-File: LICENSE
Requires-Dist: django>=4
Requires-Dist: gitpython>=3
Requires-Dist: colorlog>=6
Requires-Dist: colorama>=0.4
Requires-Dist: requests>=2.32
Requires-Dist: appdirs>=1.4
Requires-Dist: pillow>=10.3
Requires-Dist: faker
Requires-Dist: djangorestframework
Requires-Dist: djangorestframework-simplejwt
Provides-Extra: dev
Requires-Dist: pytest>=8; extra == "dev"
Requires-Dist: sphinx>=7; extra == "dev"
Requires-Dist: pre-commit; extra == "dev"
Requires-Dist: ruff; extra == "dev"
Requires-Dist: tox; extra == "dev"
Dynamic: license-file
